setup.py
vparse/__init__.py
vparse.egg-info/PKG-INFO
vparse.egg-info/SOURCES.txt
vparse.egg-info/dependency_links.txt
vparse.egg-info/not-zip-safe
vparse.egg-info/top_level.txt