Metadata-Version: 1.1
Name: vparse
Version: 0.1
Summary: Visually defined PDF interpretation in Python
Home-page: https://github.com/sbirch/vparse
Author: Sam Birch
Author-email: sam.m.birch@gmail.com
License: MIT
Platform: UNKNOWN
Classifier: Development Status :: 3 - Alpha
Classifier: License :: OSI Approved :: MIT License
Classifier: Programming Language :: Python :: 2.7
